subprocess_mock/__init__.py
subprocess_mock/__main__.py
subprocess_mock/child.py
subprocess_mock/commandline.py
subprocess_mock/commons.py
subprocess_mock/functions.py
subprocess_mock/parent.py
subprocess_mock/py.typed
subprocess_mock/streams.py
subprocess_mock/workflow.py
subprocess_mock-0.4.5.dist-info/LICENSE
subprocess_mock-0.4.5.dist-info/METADATA
subprocess_mock-0.4.5.dist-info/WHEEL
subprocess_mock-0.4.5.dist-info/top_level.txt
subprocess_mock-0.4.5.dist-info/RECORD
