Metadata-Version: 2.1
Name: subprocess-mock
Version: 0.4.5
Summary: Subprocess Mock
Author-email: Rainer Schwarzbach <rainer@blackstream.de>
License: MIT License
Project-URL: Homepage, https://gitlab.com/blackstream-x/subprocess-mock
Project-URL: Documentation, https://blackstream-x.gitlab.io/subprocess-mock
Project-URL: CI, https://gitlab.com/blackstream-x/subprocess-mock/-/pipelines
Project-URL: Bug Tracker, https://gitlab.com/blackstream-x/subprocess-mock/-/issues
Project-URL: Repository, https://gitlab.com/blackstream-x/subprocess-mock.git
Keywords: unittest,mock,subprocess
Classifier: Development Status :: 4 - Beta
Classifier: License :: OSI Approved :: MIT License
Classifier: Operating System :: OS Independent
Classifier: Programming Language :: Python :: 3
Classifier: Programming Language :: Python :: 3.6
Classifier: Programming Language :: Python :: 3.7
Classifier: Programming Language :: Python :: 3.8
Classifier: Programming Language :: Python :: 3.9
Classifier: Programming Language :: Python :: 3.10
Classifier: Programming Language :: Python :: 3.11
Classifier: Programming Language :: Python :: 3.12
Classifier: Programming Language :: Python :: 3 :: Only
Classifier: Intended Audience :: Developers
Classifier: Topic :: Software Development :: Testing :: Mocking
Classifier: Topic :: Software Development :: Testing :: Unit
Requires-Python: >=3.6
License-File: LICENSE
